codebeaver/AnalyzeError.py
codebeaver/CodebeaverConfig.py
codebeaver/ContentCleaner.py
codebeaver/E2E.py
codebeaver/GitUtils.py
codebeaver/Report.py
codebeaver/ResponseParser.py
codebeaver/TestFilePattern.py
codebeaver/UnitTestGenerator.py
codebeaver/UnitTestManager.py
codebeaver/UnitTestRunner.py
codebeaver/__init__.py
codebeaver/cli.py
codebeaver/types.py
codebeaver/models/anthropic.py
codebeaver/models/deepseek.py
codebeaver/models/mistral.py
codebeaver/models/ollama.py
codebeaver/models/openai.py
codebeaver/models/provider_factory.py
codebeaver/reporting/Report.py
codebeaver/reporting/ReportRequirements.md
codebeaver/reporting/__init__.py
codebeaver/templates/__init__.py
codebeaver/templates/bun.yml
codebeaver/templates/django.yml
codebeaver/templates/go-1.13.yml
codebeaver/templates/go-1.16.yml
codebeaver/templates/go-1.17.yml
codebeaver/templates/go-1.19.yml
codebeaver/templates/go-1.21.yml
codebeaver/templates/go-1.22.yml
codebeaver/templates/go-1.23.yml
codebeaver/templates/go-1.24.yml
codebeaver/templates/go.yml
codebeaver/templates/javascript-18-jest-npm.yml
codebeaver/templates/javascript-22-jest-npm.yml
codebeaver/templates/javascript-22-jest-pnpm.yml
codebeaver/templates/javascript-22-jest-yarn.yml
codebeaver/templates/javascript-22-vitest-npm.yml
codebeaver/templates/javascript-22-vitest-pnpm.yml
codebeaver/templates/javascript-22-vitest-yarn.yml
codebeaver/templates/jest.yml
codebeaver/templates/node-22-jest-pnpm.yml
codebeaver/templates/node-22-jest-yarn.yml
codebeaver/templates/node-22-jest.yml
codebeaver/templates/node-22-vitest-yarn.yml
codebeaver/templates/node-22-vitest.yml
codebeaver/templates/node22-jest-yarn.yml
codebeaver/templates/node22-jest.yml
codebeaver/templates/node22-vitest-yarn.yml
codebeaver/templates/node22-vitest.yml
codebeaver/templates/nyc.yml
codebeaver/templates/php.yml
codebeaver/templates/pytest.yml
codebeaver/templates/python-3.12-pytest.yml
codebeaver/templates/python-pytest-poetry.yml
codebeaver/templates/ruby.yml
codebeaver-0.1.3.dist-info/METADATA
codebeaver-0.1.3.dist-info/WHEEL
codebeaver-0.1.3.dist-info/entry_points.txt
codebeaver-0.1.3.dist-info/licenses/LICENSE
codebeaver-0.1.3.dist-info/RECORD
