Metadata-Version: 2.4
Name: codebeaver
Version: 0.1.3
Summary: CodeBeaver - Unit and E2E testing for your codebase
Project-URL: Homepage, https://www.codebeaver.ai
Project-URL: Repository, https://github.com/codebeaver-ai/codebeaver-ai
Project-URL: Issues, https://github.com/codebeaver-ai/codebeaver-ai/issues
Author-email: CodeBeaver Team <info@codebeaver.ai>
License-Expression: MIT
License-File: LICENSE
Classifier: Development Status :: 4 - Beta
Classifier: Intended Audience :: Developers
Classifier: License :: OSI Approved :: MIT License
Classifier: Programming Language :: Python :: 3.11
Requires-Python: >=3.11
Requires-Dist: aiohttp>=3.9.0
Requires-Dist: black>=23.0.0
Requires-Dist: browser-use>=0.1.40
Requires-Dist: coverage>=7.0.0
Requires-Dist: dotenv>=0.9.9
Requires-Dist: openai>=1.0.0
Requires-Dist: pydantic>=2.5.0
Requires-Dist: pygments>=2.19.1
Requires-Dist: pytest-cov>=4.0.0
Requires-Dist: pytest>=7.0.0
Requires-Dist: python-dotenv>=1.0.0
Requires-Dist: pyyaml>=6.0.0
Requires-Dist: tree-sitter-typescript>=0.23.2
Requires-Dist: tree-sitter>=0.24.0
Provides-Extra: test
Requires-Dist: flake8>=6.0.0; extra == 'test'
Requires-Dist: pytest-asyncio>=0.21.0; extra == 'test'
